CHANGES.md
MANIFEST.in
README.md
setup.py
oneprint/__init__.py
oneprint.egg-info/PKG-INFO
oneprint.egg-info/SOURCES.txt
oneprint.egg-info/dependency_links.txt
oneprint.egg-info/not-zip-safe
oneprint.egg-info/top_level.txt