Metadata-Version: 2.1
Name: oneprint
Version: 1.1.0
Summary: oneprint is a uniform print library. It use XML to define print data. Now it can convert XML to ESC/POS data or Pillow Image object.
Home-page: https://github.com/sintrb/oneprint/
Author: trb
Author-email: sintrb@gmail.com
License: UNKNOWN
Keywords: oneprint,print,xprint,escpos
Platform: UNKNOWN
